{
    "player_id": 78435,
    "full_name": "Chet Walker",
    "awards": {
        "NBA All-Star": [
            "1963-64",
            "1965-66",
            "1966-67",
            "1969-70",
            "1970-71",
            "1972-73",
            "1973-74"
        ],
        "NBA All-Star Game MVP": [],
        "MVP": [],
        "All-NBA-First": [],
        "All-NBA-Second": [],
        "All-NBA-Third": [],
        "DPOY": [],
        "All-Defensive-First": [],
        "All-Defensive-Second": [],
        "ROY": [],
        "All-Rookie-First": [
            "1962-63"
        ],
        "All-Rookie-Second": [],
        "Championships": [
            "1966-67"
        ],
        "FMVP": [],
        "Olympic Gold": [],
        "Olympic Silver": [],
        "Olympic Bronze": []
    },
    "season_stats": {
        "1962-63": {
            "PPG": 12.3,
            "APG": 1.1,
            "RBG": 7.2,
            "SPG": NaN,
            "BPG": NaN,
            "TPG": 0.0,
            "PM": NaN,
            "MPG": 25.5,
            "FG_PCT": 0.469,
            "FG3_PCT": 0,
            "FT_PCT": 0.699,
            "FGM": 352,
            "FGA": 751,
            "FG3M": null,
            "FG3A": null,
            "FTM": 253,
            "FTA": 362,
            "GP": 78
        },
        "1963-64": {
            "PPG": 17.3,
            "APG": 1.6,
            "RBG": 10.3,
            "SPG": NaN,
            "BPG": NaN,
            "TPG": 0.0,
            "PM": NaN,
            "MPG": 36.5,
            "FG_PCT": 0.44,
            "FG3_PCT": 0,
            "FT_PCT": 0.711,
            "FGM": 492,
            "FGA": 1118,
            "FG3M": null,
            "FG3A": null,
            "FTM": 330,
            "FTA": 464,
            "GP": 76
        },
        "1964-65": {
            "PPG": 13.2,
            "APG": 1.7,
            "RBG": 6.7,
            "SPG": NaN,
            "BPG": NaN,
            "TPG": 0.0,
            "PM": NaN,
            "MPG": 27.7,
            "FG_PCT": 0.403,
            "FG3_PCT": 0,
            "FT_PCT": 0.742,
            "FGM": 377,
            "FGA": 936,
            "FG3M": null,
            "FG3A": null,
            "FTM": 288,
            "FTA": 388,
            "GP": 79
        },
        "1965-66": {
            "PPG": 15.3,
            "APG": 2.5,
            "RBG": 8.0,
            "SPG": NaN,
            "BPG": NaN,
            "TPG": 0.0,
            "PM": NaN,
            "MPG": 32.5,
            "FG_PCT": 0.451,
            "FG3_PCT": 0,
            "FT_PCT": 0.716,
            "FGM": 443,
            "FGA": 982,
            "FG3M": null,
            "FG3A": null,
            "FTM": 335,
            "FTA": 468,
            "GP": 80
        },
        "1966-67": {
            "PPG": 19.3,
            "APG": 2.3,
            "RBG": 8.1,
            "SPG": NaN,
            "BPG": NaN,
            "TPG": 0.0,
            "PM": NaN,
            "MPG": 33.2,
            "FG_PCT": 0.488,
            "FG3_PCT": 0,
            "FT_PCT": 0.766,
            "FGM": 561,
            "FGA": 1150,
            "FG3M": null,
            "FG3A": null,
            "FTM": 445,
            "FTA": 581,
            "GP": 81
        },
        "1967-68": {
            "PPG": 17.9,
            "APG": 1.9,
            "RBG": 7.4,
            "SPG": NaN,
            "BPG": NaN,
            "TPG": 0.0,
            "PM": NaN,
            "MPG": 32.0,
            "FG_PCT": 0.46,
            "FG3_PCT": 0,
            "FT_PCT": 0.726,
            "FGM": 539,
            "FGA": 1172,
            "FG3M": null,
            "FG3A": null,
            "FTM": 387,
            "FTA": 533,
            "GP": 82
        },
        "1968-69": {
            "PPG": 18.0,
            "APG": 1.8,
            "RBG": 7.8,
            "SPG": NaN,
            "BPG": NaN,
            "TPG": 0.0,
            "PM": NaN,
            "MPG": 33.6,
            "FG_PCT": 0.484,
            "FG3_PCT": 0,
            "FT_PCT": 0.804,
            "FGM": 554,
            "FGA": 1145,
            "FG3M": null,
            "FG3A": null,
            "FTM": 369,
            "FTA": 459,
            "GP": 82
        },
        "1969-70": {
            "PPG": 21.5,
            "APG": 2.5,
            "RBG": 7.7,
            "SPG": NaN,
            "BPG": NaN,
            "TPG": 0.0,
            "PM": NaN,
            "MPG": 34.9,
            "FG_PCT": 0.477,
            "FG3_PCT": 0,
            "FT_PCT": 0.85,
            "FGM": 596,
            "FGA": 1249,
            "FG3M": null,
            "FG3A": null,
            "FTM": 483,
            "FTA": 568,
            "GP": 78
        },
        "1970-71": {
            "PPG": 22.0,
            "APG": 2.2,
            "RBG": 7.3,
            "SPG": NaN,
            "BPG": NaN,
            "TPG": 0.0,
            "PM": NaN,
            "MPG": 36.1,
            "FG_PCT": 0.465,
            "FG3_PCT": 0,
            "FT_PCT": 0.859,
            "FGM": 650,
            "FGA": 1398,
            "FG3M": null,
            "FG3A": null,
            "FTM": 480,
            "FTA": 559,
            "GP": 81
        },
        "1971-72": {
            "PPG": 22.0,
            "APG": 2.3,
            "RBG": 6.1,
            "SPG": NaN,
            "BPG": NaN,
            "TPG": 0.0,
            "PM": NaN,
            "MPG": 33.2,
            "FG_PCT": 0.505,
            "FG3_PCT": 0,
            "FT_PCT": 0.847,
            "FGM": 619,
            "FGA": 1225,
            "FG3M": null,
            "FG3A": null,
            "FTM": 481,
            "FTA": 568,
            "GP": 78
        },
        "1972-73": {
            "PPG": 19.9,
            "APG": 2.3,
            "RBG": 5.0,
            "SPG": NaN,
            "BPG": NaN,
            "TPG": 0.0,
            "PM": NaN,
            "MPG": 31.1,
            "FG_PCT": 0.478,
            "FG3_PCT": 0,
            "FT_PCT": 0.832,
            "FGM": 597,
            "FGA": 1248,
            "FG3M": null,
            "FG3A": null,
            "FTM": 376,
            "FTA": 452,
            "GP": 79
        },
        "1973-74": {
            "PPG": 19.3,
            "APG": 2.4,
            "RBG": 5.0,
            "SPG": 0.8,
            "BPG": 0.0,
            "TPG": 0.0,
            "PM": NaN,
            "MPG": 32.5,
            "FG_PCT": 0.486,
            "FG3_PCT": 0,
            "FT_PCT": 0.875,
            "FGM": 572,
            "FGA": 1178,
            "FG3M": null,
            "FG3A": null,
            "FTM": 439,
            "FTA": 502,
            "GP": 82
        },
        "1974-75": {
            "PPG": 19.2,
            "APG": 2.2,
            "RBG": 5.7,
            "SPG": 0.6,
            "BPG": 0.1,
            "TPG": 0.0,
            "PM": NaN,
            "MPG": 32.3,
            "FG_PCT": 0.487,
            "FG3_PCT": 0,
            "FT_PCT": 0.86,
            "FGM": 524,
            "FGA": 1076,
            "FG3M": null,
            "FG3A": null,
            "FTM": 413,
            "FTA": 480,
            "GP": 76
        }
    },
    "playoff_stats": {
        "1962-63": {
            "PPG": 15.2,
            "APG": 1.8,
            "RBG": 9.4,
            "SPG": NaN,
            "BPG": NaN,
            "TPG": 0.0,
            "PM": NaN,
            "MPG": 26.0,
            "FG_PCT": 0.509,
            "FG3_PCT": 0,
            "FT_PCT": 0.733,
            "FGM": 27,
            "FGA": 53,
            "FG3M": null,
            "FG3A": null,
            "FTM": 22,
            "FTA": 30,
            "GP": 5
        },
        "1963-64": {
            "PPG": 18.8,
            "APG": 2.6,
            "RBG": 10.4,
            "SPG": NaN,
            "BPG": NaN,
            "TPG": 0.0,
            "PM": NaN,
            "MPG": 38.0,
            "FG_PCT": 0.39,
            "FG3_PCT": 0,
            "FT_PCT": 0.739,
            "FGM": 30,
            "FGA": 77,
            "FG3M": null,
            "FG3A": null,
            "FTM": 34,
            "FTA": 46,
            "GP": 5
        },
        "1964-65": {
            "PPG": 20.3,
            "APG": 1.6,
            "RBG": 7.2,
            "SPG": NaN,
            "BPG": NaN,
            "TPG": 0.0,
            "PM": NaN,
            "MPG": 42.6,
            "FG_PCT": 0.48,
            "FG3_PCT": 0,
            "FT_PCT": 0.76,
            "FGM": 83,
            "FGA": 173,
            "FG3M": null,
            "FG3A": null,
            "FTM": 57,
            "FTA": 75,
            "GP": 11
        },
        "1965-66": {
            "PPG": 14.6,
            "APG": 3.0,
            "RBG": 7.4,
            "SPG": NaN,
            "BPG": NaN,
            "TPG": 0.0,
            "PM": NaN,
            "MPG": 36.2,
            "FG_PCT": 0.375,
            "FG3_PCT": 0,
            "FT_PCT": 0.806,
            "FGM": 24,
            "FGA": 64,
            "FG3M": null,
            "FG3A": null,
            "FTM": 25,
            "FTA": 31,
            "GP": 5
        },
        "1966-67": {
            "PPG": 21.7,
            "APG": 2.1,
            "RBG": 7.6,
            "SPG": NaN,
            "BPG": NaN,
            "TPG": 0.0,
            "PM": NaN,
            "MPG": 36.7,
            "FG_PCT": 0.467,
            "FG3_PCT": 0,
            "FT_PCT": 0.807,
            "FGM": 115,
            "FGA": 246,
            "FG3M": null,
            "FG3A": null,
            "FTM": 96,
            "FTA": 119,
            "GP": 15
        },
        "1967-68": {
            "PPG": 19.1,
            "APG": 1.8,
            "RBG": 7.4,
            "SPG": NaN,
            "BPG": NaN,
            "TPG": 0.0,
            "PM": NaN,
            "MPG": 37.3,
            "FG_PCT": 0.41,
            "FG3_PCT": 0,
            "FT_PCT": 0.679,
            "FGM": 86,
            "FGA": 210,
            "FG3M": null,
            "FG3A": null,
            "FTM": 76,
            "FTA": 112,
            "GP": 13
        },
        "1968-69": {
            "PPG": 13.5,
            "APG": 2.0,
            "RBG": 5.8,
            "SPG": NaN,
            "BPG": NaN,
            "TPG": 0.0,
            "PM": NaN,
            "MPG": 27.2,
            "FG_PCT": 0.535,
            "FG3_PCT": 0,
            "FT_PCT": 0.667,
            "FGM": 23,
            "FGA": 43,
            "FG3M": null,
            "FG3A": null,
            "FTM": 8,
            "FTA": 12,
            "GP": 4
        },
        "1969-70": {
            "PPG": 19.4,
            "APG": 2.2,
            "RBG": 8.4,
            "SPG": NaN,
            "BPG": NaN,
            "TPG": 0.0,
            "PM": NaN,
            "MPG": 35.6,
            "FG_PCT": 0.422,
            "FG3_PCT": 0,
            "FT_PCT": 0.818,
            "FGM": 35,
            "FGA": 83,
            "FG3M": null,
            "FG3A": null,
            "FTM": 27,
            "FTA": 33,
            "GP": 5
        },
        "1970-71": {
            "PPG": 15.0,
            "APG": 3.1,
            "RBG": 7.1,
            "SPG": NaN,
            "BPG": NaN,
            "TPG": 0.0,
            "PM": NaN,
            "MPG": 33.4,
            "FG_PCT": 0.44,
            "FG3_PCT": 0,
            "FT_PCT": 0.708,
            "FGM": 44,
            "FGA": 100,
            "FG3M": null,
            "FG3A": null,
            "FTM": 17,
            "FTA": 24,
            "GP": 7
        },
        "1971-72": {
            "PPG": 11.2,
            "APG": 1.0,
            "RBG": 3.5,
            "SPG": NaN,
            "BPG": NaN,
            "TPG": 0.0,
            "PM": NaN,
            "MPG": 24.2,
            "FG_PCT": 0.421,
            "FG3_PCT": 0,
            "FT_PCT": 0.813,
            "FGM": 16,
            "FGA": 38,
            "FG3M": null,
            "FG3A": null,
            "FTM": 13,
            "FTA": 16,
            "GP": 4
        },
        "1972-73": {
            "PPG": 16.7,
            "APG": 2.0,
            "RBG": 8.9,
            "SPG": NaN,
            "BPG": NaN,
            "TPG": 0.0,
            "PM": NaN,
            "MPG": 32.7,
            "FG_PCT": 0.347,
            "FG3_PCT": 0,
            "FT_PCT": 0.892,
            "FGM": 42,
            "FGA": 121,
            "FG3M": null,
            "FG3A": null,
            "FTM": 33,
            "FTA": 37,
            "GP": 7
        },
        "1973-74": {
            "PPG": 20.9,
            "APG": 1.6,
            "RBG": 5.5,
            "SPG": 0.9,
            "BPG": 0.1,
            "TPG": 0.0,
            "PM": NaN,
            "MPG": 36.6,
            "FG_PCT": 0.509,
            "FG3_PCT": 0,
            "FT_PCT": 0.861,
            "FGM": 81,
            "FGA": 159,
            "FG3M": null,
            "FG3A": null,
            "FTM": 68,
            "FTA": 79,
            "GP": 11
        },
        "1974-75": {
            "PPG": 17.5,
            "APG": 1.8,
            "RBG": 4.6,
            "SPG": 1.0,
            "BPG": 0.1,
            "TPG": 0.0,
            "PM": NaN,
            "MPG": 33.2,
            "FG_PCT": 0.494,
            "FG3_PCT": 0,
            "FT_PCT": 0.88,
            "FGM": 81,
            "FGA": 164,
            "FG3M": null,
            "FG3A": null,
            "FTM": 66,
            "FTA": 75,
            "GP": 13
        }
    },
    "specs": {
        "Height": 79,
        "Weight": "212",
        "Position": "Forward",
        "Teams": [
            "SYR",
            "PHL",
            "CHI"
        ],
        "DraftRound": "2",
        "DraftNumber": "12",
        "Active": false
    }
}