{
    "player_id": 934,
    "full_name": "Derrick Coleman",
    "awards": {
        "NBA All-Star": [
            "1993-94"
        ],
        "NBA All-Star Game MVP": [],
        "MVP": [],
        "All-NBA-First": [],
        "All-NBA-Second": [],
        "All-NBA-Third": [
            "1992-93",
            "1993-94"
        ],
        "DPOY": [],
        "All-Defensive-First": [],
        "All-Defensive-Second": [],
        "ROY": [
            "1990-91"
        ],
        "All-Rookie-First": [
            "1990-91"
        ],
        "All-Rookie-Second": [],
        "Championships": [],
        "FMVP": [],
        "Olympic Gold": [],
        "Olympic Silver": [],
        "Olympic Bronze": []
    },
    "season_stats": {
        "1990-91": {
            "PPG": 18.4,
            "APG": 2.2,
            "RBG": 10.3,
            "SPG": 1.0,
            "BPG": 1.3,
            "TPG": 2.9,
            "PM": NaN,
            "MPG": 35.2,
            "FG_PCT": 0.467,
            "FG3_PCT": 0.342,
            "FT_PCT": 0.731,
            "FGM": 514,
            "FGA": 1100,
            "FG3M": 13,
            "FG3A": 38,
            "FTM": 323,
            "FTA": 442,
            "GP": 74
        },
        "1991-92": {
            "PPG": 19.8,
            "APG": 3.2,
            "RBG": 9.5,
            "SPG": 0.8,
            "BPG": 1.5,
            "TPG": 3.8,
            "PM": NaN,
            "MPG": 34.0,
            "FG_PCT": 0.504,
            "FG3_PCT": 0.303,
            "FT_PCT": 0.763,
            "FGM": 483,
            "FGA": 958,
            "FG3M": 23,
            "FG3A": 76,
            "FTM": 300,
            "FTA": 393,
            "GP": 65
        },
        "1992-93": {
            "PPG": 20.7,
            "APG": 3.6,
            "RBG": 11.2,
            "SPG": 1.2,
            "BPG": 1.7,
            "TPG": 3.2,
            "PM": NaN,
            "MPG": 36.3,
            "FG_PCT": 0.46,
            "FG3_PCT": 0.232,
            "FT_PCT": 0.808,
            "FGM": 564,
            "FGA": 1226,
            "FG3M": 23,
            "FG3A": 99,
            "FTM": 421,
            "FTA": 521,
            "GP": 76
        },
        "1993-94": {
            "PPG": 20.2,
            "APG": 3.4,
            "RBG": 11.3,
            "SPG": 0.9,
            "BPG": 1.8,
            "TPG": 2.7,
            "PM": NaN,
            "MPG": 36.1,
            "FG_PCT": 0.447,
            "FG3_PCT": 0.314,
            "FT_PCT": 0.774,
            "FGM": 541,
            "FGA": 1209,
            "FG3M": 38,
            "FG3A": 121,
            "FTM": 439,
            "FTA": 567,
            "GP": 77
        },
        "1994-95": {
            "PPG": 20.5,
            "APG": 3.3,
            "RBG": 10.6,
            "SPG": 0.6,
            "BPG": 1.7,
            "TPG": 3.1,
            "PM": NaN,
            "MPG": 37.6,
            "FG_PCT": 0.424,
            "FG3_PCT": 0.233,
            "FT_PCT": 0.767,
            "FGM": 371,
            "FGA": 875,
            "FG3M": 28,
            "FG3A": 120,
            "FTM": 376,
            "FTA": 490,
            "GP": 56
        },
        "1995-96": {
            "PPG": 11.2,
            "APG": 2.8,
            "RBG": 6.5,
            "SPG": 0.4,
            "BPG": 0.9,
            "TPG": 2.5,
            "PM": NaN,
            "MPG": 26.7,
            "FG_PCT": 0.407,
            "FG3_PCT": 0.333,
            "FT_PCT": 0.625,
            "FGM": 48,
            "FGA": 118,
            "FG3M": 7,
            "FG3A": 21,
            "FTM": 20,
            "FTA": 32,
            "GP": 11
        },
        "1996-97": {
            "PPG": 18.1,
            "APG": 3.4,
            "RBG": 10.1,
            "SPG": 0.9,
            "BPG": 1.3,
            "TPG": 3.2,
            "PM": -3.6,
            "MPG": 36.8,
            "FG_PCT": 0.435,
            "FG3_PCT": 0.269,
            "FT_PCT": 0.745,
            "FGM": 364,
            "FGA": 836,
            "FG3M": 32,
            "FG3A": 119,
            "FTM": 272,
            "FTA": 365,
            "GP": 57
        },
        "1997-98": {
            "PPG": 17.6,
            "APG": 2.5,
            "RBG": 9.9,
            "SPG": 0.8,
            "BPG": 1.2,
            "TPG": 2.7,
            "PM": -0.8,
            "MPG": 36.2,
            "FG_PCT": 0.411,
            "FG3_PCT": 0.265,
            "FT_PCT": 0.772,
            "FGM": 356,
            "FGA": 867,
            "FG3M": 26,
            "FG3A": 98,
            "FTM": 302,
            "FTA": 391,
            "GP": 59
        },
        "1998-99": {
            "PPG": 13.1,
            "APG": 2.1,
            "RBG": 8.9,
            "SPG": 0.6,
            "BPG": 1.1,
            "TPG": 2.4,
            "PM": -2.5,
            "MPG": 31.8,
            "FG_PCT": 0.414,
            "FG3_PCT": 0.212,
            "FT_PCT": 0.753,
            "FGM": 168,
            "FGA": 406,
            "FG3M": 7,
            "FG3A": 33,
            "FTM": 143,
            "FTA": 190,
            "GP": 37
        },
        "1999-00": {
            "PPG": 16.7,
            "APG": 2.4,
            "RBG": 8.5,
            "SPG": 0.5,
            "BPG": 1.8,
            "TPG": 2.3,
            "PM": 1.0,
            "MPG": 31.7,
            "FG_PCT": 0.456,
            "FG3_PCT": 0.362,
            "FT_PCT": 0.785,
            "FGM": 446,
            "FGA": 979,
            "FG3M": 51,
            "FG3A": 141,
            "FTM": 296,
            "FTA": 377,
            "GP": 74
        },
        "2000-01": {
            "PPG": 8.1,
            "APG": 1.1,
            "RBG": 5.4,
            "SPG": 0.3,
            "BPG": 0.6,
            "TPG": 1.2,
            "PM": -3.2,
            "MPG": 20.1,
            "FG_PCT": 0.38,
            "FG3_PCT": 0.392,
            "FT_PCT": 0.685,
            "FGM": 97,
            "FGA": 255,
            "FG3M": 20,
            "FG3A": 51,
            "FTM": 63,
            "FTA": 92,
            "GP": 34
        },
        "2001-02": {
            "PPG": 15.1,
            "APG": 1.7,
            "RBG": 8.8,
            "SPG": 0.7,
            "BPG": 0.9,
            "TPG": 2.1,
            "PM": 1.9,
            "MPG": 35.9,
            "FG_PCT": 0.45,
            "FG3_PCT": 0.337,
            "FT_PCT": 0.815,
            "FGM": 331,
            "FGA": 735,
            "FG3M": 28,
            "FG3A": 83,
            "FTM": 185,
            "FTA": 227,
            "GP": 58
        },
        "2002-03": {
            "PPG": 9.4,
            "APG": 1.4,
            "RBG": 7.0,
            "SPG": 0.8,
            "BPG": 1.1,
            "TPG": 1.5,
            "PM": 3.9,
            "MPG": 27.2,
            "FG_PCT": 0.448,
            "FG3_PCT": 0.328,
            "FT_PCT": 0.784,
            "FGM": 223,
            "FGA": 498,
            "FG3M": 22,
            "FG3A": 67,
            "FTM": 134,
            "FTA": 171,
            "GP": 64
        },
        "2003-04": {
            "PPG": 8.0,
            "APG": 1.4,
            "RBG": 5.6,
            "SPG": 0.7,
            "BPG": 0.8,
            "TPG": 1.7,
            "PM": -2.1,
            "MPG": 24.8,
            "FG_PCT": 0.413,
            "FG3_PCT": 0.222,
            "FT_PCT": 0.754,
            "FGM": 107,
            "FGA": 259,
            "FG3M": 8,
            "FG3A": 36,
            "FTM": 49,
            "FTA": 65,
            "GP": 34
        },
        "2004-05": {
            "PPG": 1.8,
            "APG": 0.0,
            "RBG": 3.0,
            "SPG": 0.0,
            "BPG": 0.0,
            "TPG": 0.4,
            "PM": -3.8,
            "MPG": 10.0,
            "FG_PCT": 0.214,
            "FG3_PCT": 0,
            "FT_PCT": 1.0,
            "FGM": 3,
            "FGA": 14,
            "FG3M": 0,
            "FG3A": 2,
            "FTM": 3,
            "FTA": 3,
            "GP": 5
        }
    },
    "playoff_stats": {
        "1991-92": {
            "PPG": 22.2,
            "APG": 5.2,
            "RBG": 11.2,
            "SPG": 1.8,
            "BPG": 1.0,
            "TPG": 2.8,
            "PM": NaN,
            "MPG": 40.5,
            "FG_PCT": 0.486,
            "FG3_PCT": 0.167,
            "FT_PCT": 0.762,
            "FGM": 36,
            "FGA": 74,
            "FG3M": 1,
            "FG3A": 6,
            "FTM": 16,
            "FTA": 21,
            "GP": 4
        },
        "1992-93": {
            "PPG": 26.8,
            "APG": 4.6,
            "RBG": 13.4,
            "SPG": 1.2,
            "BPG": 2.6,
            "TPG": 2.6,
            "PM": NaN,
            "MPG": 45.0,
            "FG_PCT": 0.532,
            "FG3_PCT": 0.417,
            "FT_PCT": 0.806,
            "FGM": 50,
            "FGA": 94,
            "FG3M": 5,
            "FG3A": 12,
            "FTM": 29,
            "FTA": 36,
            "GP": 5
        },
        "1993-94": {
            "PPG": 24.5,
            "APG": 2.5,
            "RBG": 14.2,
            "SPG": 0.5,
            "BPG": 1.2,
            "TPG": 4.5,
            "PM": NaN,
            "MPG": 43.2,
            "FG_PCT": 0.397,
            "FG3_PCT": 0.556,
            "FT_PCT": 0.78,
            "FGM": 27,
            "FGA": 68,
            "FG3M": 5,
            "FG3A": 9,
            "FTM": 39,
            "FTA": 50,
            "GP": 4
        },
        "1999-00": {
            "PPG": 20.2,
            "APG": 3.5,
            "RBG": 12.5,
            "SPG": 0.8,
            "BPG": 3.0,
            "TPG": 3.2,
            "PM": -5.2,
            "MPG": 42.2,
            "FG_PCT": 0.474,
            "FG3_PCT": 0.313,
            "FT_PCT": 0.786,
            "FGM": 27,
            "FGA": 57,
            "FG3M": 5,
            "FG3A": 16,
            "FTM": 22,
            "FTA": 28,
            "GP": 4
        },
        "2000-01": {
            "PPG": 5.4,
            "APG": 1.2,
            "RBG": 5.0,
            "SPG": 0.8,
            "BPG": 0.4,
            "TPG": 1.0,
            "PM": 4.6,
            "MPG": 17.6,
            "FG_PCT": 0.265,
            "FG3_PCT": 0.25,
            "FT_PCT": 0.778,
            "FGM": 9,
            "FGA": 34,
            "FG3M": 2,
            "FG3A": 8,
            "FTM": 7,
            "FTA": 9,
            "GP": 5
        },
        "2001-02": {
            "PPG": 12.8,
            "APG": 2.0,
            "RBG": 9.2,
            "SPG": 0.2,
            "BPG": 1.4,
            "TPG": 1.0,
            "PM": -5.2,
            "MPG": 38.2,
            "FG_PCT": 0.524,
            "FG3_PCT": 0.308,
            "FT_PCT": 0.8,
            "FGM": 22,
            "FGA": 42,
            "FG3M": 4,
            "FG3A": 13,
            "FTM": 16,
            "FTA": 20,
            "GP": 5
        },
        "2002-03": {
            "PPG": 13.6,
            "APG": 2.0,
            "RBG": 8.0,
            "SPG": 0.6,
            "BPG": 1.3,
            "TPG": 1.4,
            "PM": 2.8,
            "MPG": 37.4,
            "FG_PCT": 0.5,
            "FG3_PCT": 0.4,
            "FT_PCT": 0.872,
            "FGM": 59,
            "FGA": 118,
            "FG3M": 4,
            "FG3A": 10,
            "FTM": 41,
            "FTA": 47,
            "GP": 12
        }
    },
    "specs": {
        "Height": 82,
        "Weight": "270",
        "Position": "Forward",
        "Teams": [
            "NJN",
            "PHL",
            "PHI",
            "CHH",
            "DET"
        ],
        "DraftRound": "1",
        "DraftNumber": "1",
        "Active": false
    }
}