{
    "player_id": 1628537,
    "full_name": "Jaylen Morris",
    "awards": {
        "NBA All-Star": [],
        "NBA All-Star Game MVP": [],
        "MVP": [],
        "All-NBA-First": [],
        "All-NBA-Second": [],
        "All-NBA-Third": [],
        "DPOY": [],
        "All-Defensive-First": [],
        "All-Defensive-Second": [],
        "ROY": [],
        "All-Rookie-First": [],
        "All-Rookie-Second": [],
        "Championships": [],
        "FMVP": [],
        "Olympic Gold": [],
        "Olympic Silver": [],
        "Olympic Bronze": []
    },
    "season_stats": {
        "2017-18": {
            "PPG": 4.7,
            "APG": 1.2,
            "RBG": 2.7,
            "SPG": 0.3,
            "BPG": 0.2,
            "TPG": 1.0,
            "PM": -7.0,
            "MPG": 16.3,
            "FG_PCT": 0.406,
            "FG3_PCT": 0.2,
            "FT_PCT": 0,
            "FGM": 13,
            "FGA": 32,
            "FG3M": 2,
            "FG3A": 10,
            "FTM": 0,
            "FTA": 0,
            "GP": 6
        },
        "2018-19": {
            "PPG": 2.5,
            "APG": 1.0,
            "RBG": 1.2,
            "SPG": 0.5,
            "BPG": 0.0,
            "TPG": 0.2,
            "PM": 3.0,
            "MPG": 7.2,
            "FG_PCT": 0.4,
            "FG3_PCT": 0.333,
            "FT_PCT": 0.5,
            "FGM": 4,
            "FGA": 10,
            "FG3M": 1,
            "FG3A": 3,
            "FTM": 1,
            "FTA": 2,
            "GP": 4
        },
        "2021-22": {
            "PPG": 0.7,
            "APG": 0.7,
            "RBG": 0.7,
            "SPG": 0.0,
            "BPG": 0.0,
            "TPG": 0.3,
            "PM": 2.7,
            "MPG": 5.3,
            "FG_PCT": 0,
            "FG3_PCT": 0,
            "FT_PCT": 0.5,
            "FGM": 0,
            "FGA": 6,
            "FG3M": 0,
            "FG3A": 2,
            "FTM": 2,
            "FTA": 4,
            "GP": 3
        }
    },
    "playoff_stats": {},
    "specs": {
        "Height": 77,
        "Weight": "185",
        "Position": "Guard",
        "Teams": [
            "ATL",
            "MIL",
            "SAS"
        ],
        "DraftRound": "Undrafted",
        "DraftNumber": "Undrafted",
        "Active": false
    }
}