{
    "player_id": 2244,
    "full_name": "Jeff Trepagnier",
    "awards": {
        "NBA All-Star": [],
        "NBA All-Star Game MVP": [],
        "MVP": [],
        "All-NBA-First": [],
        "All-NBA-Second": [],
        "All-NBA-Third": [],
        "DPOY": [],
        "All-Defensive-First": [],
        "All-Defensive-Second": [],
        "ROY": [],
        "All-Rookie-First": [],
        "All-Rookie-Second": [],
        "Championships": [],
        "FMVP": [],
        "Olympic Gold": [],
        "Olympic Silver": [],
        "Olympic Bronze": []
    },
    "season_stats": {
        "2001-02": {
            "PPG": 1.5,
            "APG": 1.0,
            "RBG": 1.0,
            "SPG": 0.7,
            "BPG": 0.3,
            "TPG": 0.9,
            "PM": 1.2,
            "MPG": 6.3,
            "FG_PCT": 0.304,
            "FG3_PCT": 0,
            "FT_PCT": 0.571,
            "FGM": 7,
            "FGA": 23,
            "FG3M": 0,
            "FG3A": 1,
            "FTM": 4,
            "FTA": 7,
            "GP": 12
        },
        "2002-03": {
            "PPG": 5.6,
            "APG": 0.8,
            "RBG": 2.0,
            "SPG": 1.0,
            "BPG": 0.0,
            "TPG": 1.0,
            "PM": -0.6,
            "MPG": 12.1,
            "FG_PCT": 0.425,
            "FG3_PCT": 0.5,
            "FT_PCT": 1.0,
            "FGM": 17,
            "FGA": 40,
            "FG3M": 4,
            "FG3A": 8,
            "FTM": 7,
            "FTA": 7,
            "GP": 8
        },
        "2003-04": {
            "PPG": 2.3,
            "APG": 0.4,
            "RBG": 1.4,
            "SPG": 0.3,
            "BPG": 0.0,
            "TPG": 0.5,
            "PM": -2.2,
            "MPG": 8.7,
            "FG_PCT": 0.263,
            "FG3_PCT": 0.5,
            "FT_PCT": 0.5,
            "FGM": 10,
            "FGA": 38,
            "FG3M": 2,
            "FG3A": 4,
            "FTM": 3,
            "FTA": 6,
            "GP": 11
        }
    },
    "playoff_stats": {},
    "specs": {
        "Height": 76,
        "Weight": "200",
        "Position": "Guard",
        "Teams": [
            "CLE",
            "DEN"
        ],
        "DraftRound": "2",
        "DraftNumber": "35",
        "Active": false
    }
}