{
    "player_id": 76321,
    "full_name": "Marty Byrnes",
    "awards": {
        "NBA All-Star": [],
        "NBA All-Star Game MVP": [],
        "MVP": [],
        "All-NBA-First": [],
        "All-NBA-Second": [],
        "All-NBA-Third": [],
        "DPOY": [],
        "All-Defensive-First": [],
        "All-Defensive-Second": [],
        "ROY": [],
        "All-Rookie-First": [],
        "All-Rookie-Second": [],
        "Championships": [
            "1979-80"
        ],
        "FMVP": [],
        "Olympic Gold": [],
        "Olympic Silver": [],
        "Olympic Bronze": []
    },
    "season_stats": {
        "1978-79": {
            "PPG": 6.1,
            "APG": 1.3,
            "RBG": 2.4,
            "SPG": 0.3,
            "BPG": 0.1,
            "TPG": 1.5,
            "PM": NaN,
            "MPG": 16.0,
            "FG_PCT": 0.481,
            "FG3_PCT": NaN,
            "FT_PCT": 0.688,
            "FGM": 187,
            "FGA": 389,
            "FG3M": NaN,
            "FG3A": NaN,
            "FTM": 106,
            "FTA": 154,
            "GP": 79
        },
        "1979-80": {
            "PPG": 2.0,
            "APG": 0.4,
            "RBG": 0.8,
            "SPG": 0.2,
            "BPG": 0.0,
            "TPG": 0.7,
            "PM": NaN,
            "MPG": 6.1,
            "FG_PCT": 0.5,
            "FG3_PCT": NaN,
            "FT_PCT": 0.867,
            "FGM": 25,
            "FGA": 50,
            "FG3M": 0.0,
            "FG3A": 0.0,
            "FTM": 13,
            "FTA": 15,
            "GP": 32
        },
        "1980-81": {
            "PPG": 7.8,
            "APG": 1.6,
            "RBG": 2.5,
            "SPG": 0.4,
            "BPG": 0.2,
            "TPG": 0.8,
            "PM": NaN,
            "MPG": 18.9,
            "FG_PCT": 0.479,
            "FG3_PCT": 0.45,
            "FT_PCT": 0.764,
            "FGM": 216,
            "FGA": 451,
            "FG3M": 9.0,
            "FG3A": 20.0,
            "FTM": 120,
            "FTA": 157,
            "GP": 72
        },
        "1982-83": {
            "PPG": 4.9,
            "APG": 2.2,
            "RBG": 2.4,
            "SPG": 0.5,
            "BPG": 0.1,
            "TPG": 0.9,
            "PM": NaN,
            "MPG": 17.9,
            "FG_PCT": 0.42,
            "FG3_PCT": 0.231,
            "FT_PCT": 0.747,
            "FGM": 157,
            "FGA": 374,
            "FG3M": 6.0,
            "FG3A": 26.0,
            "FTM": 71,
            "FTA": 95,
            "GP": 80
        }
    },
    "playoff_stats": {
        "1979-80": {
            "PPG": 1.5,
            "APG": 0.2,
            "RBG": 0.2,
            "SPG": 0.0,
            "BPG": 0.0,
            "TPG": 0.2,
            "PM": NaN,
            "MPG": 2.0,
            "FG_PCT": 0.333,
            "FG3_PCT": 0,
            "FT_PCT": 0.667,
            "FGM": 1,
            "FGA": 3,
            "FG3M": 0,
            "FG3A": 0,
            "FTM": 4,
            "FTA": 6,
            "GP": 4
        }
    },
    "specs": {
        "Height": 79,
        "Weight": "215",
        "Position": "Forward",
        "Teams": [
            "PHX",
            "NOJ",
            "TOT",
            "LAL",
            "DAL",
            "IND"
        ],
        "DraftRound": "1",
        "DraftNumber": "19",
        "Active": false
    }
}