{
    "player_id": 77458,
    "full_name": "Peter Maravich",
    "awards": {
        "NBA All-Star": [],
        "NBA All-Star Game MVP": [],
        "MVP": [],
        "All-NBA-First": [],
        "All-NBA-Second": [],
        "All-NBA-Third": [],
        "DPOY": [],
        "All-Defensive-First": [],
        "All-Defensive-Second": [],
        "ROY": [],
        "All-Rookie-First": [],
        "All-Rookie-Second": [],
        "Championships": [],
        "FMVP": [],
        "Olympic Gold": [],
        "Olympic Silver": [],
        "Olympic Bronze": []
    },
    "season_stats": {
        "1946-47": {
            "PPG": 4.6,
            "APG": 0.1,
            "RBG": 0.0,
            "SPG": 0.0,
            "BPG": 0.0,
            "TPG": 0.0,
            "PM": NaN,
            "MPG": 0.0,
            "FG_PCT": 0.272,
            "FG3_PCT": 0,
            "FT_PCT": 0.517,
            "FGM": 102,
            "FGA": 375,
            "FG3M": null,
            "FG3A": null,
            "FTM": 30,
            "FTA": 58,
            "GP": 51
        }
    },
    "playoff_stats": {},
    "specs": {
        "Height": 72,
        "Weight": "185",
        "Position": "Guard",
        "Teams": [
            "PIT"
        ],
        "DraftRound": "Undrafted",
        "DraftNumber": "Undrafted",
        "Active": false
    }
}