{
    "player_id": 76736,
    "full_name": "Phil Ford",
    "awards": {
        "NBA All-Star": [],
        "NBA All-Star Game MVP": [],
        "MVP": [],
        "All-NBA-First": [],
        "All-NBA-Second": [
            "1978-79"
        ],
        "All-NBA-Third": [],
        "DPOY": [],
        "All-Defensive-First": [],
        "All-Defensive-Second": [],
        "ROY": [
            "1978-79"
        ],
        "All-Rookie-First": [
            "1978-79"
        ],
        "All-Rookie-Second": [],
        "Championships": [],
        "FMVP": [],
        "Olympic Gold": [
            "1976"
        ],
        "Olympic Silver": [],
        "Olympic Bronze": []
    },
    "season_stats": {
        "1978-79": {
            "PPG": 15.9,
            "APG": 8.6,
            "RBG": 2.3,
            "SPG": 2.2,
            "BPG": 0.1,
            "TPG": 4.1,
            "PM": NaN,
            "MPG": 34.5,
            "FG_PCT": 0.465,
            "FG3_PCT": NaN,
            "FT_PCT": 0.813,
            "FGM": 467,
            "FGA": 1004,
            "FG3M": NaN,
            "FG3A": NaN,
            "FTM": 326,
            "FTA": 401,
            "GP": 79
        },
        "1979-80": {
            "PPG": 16.2,
            "APG": 7.4,
            "RBG": 2.1,
            "SPG": 1.7,
            "BPG": 0.0,
            "TPG": 3.4,
            "PM": NaN,
            "MPG": 32.0,
            "FG_PCT": 0.462,
            "FG3_PCT": 0.174,
            "FT_PCT": 0.818,
            "FGM": 489,
            "FGA": 1058,
            "FG3M": 4.0,
            "FG3A": 23.0,
            "FTM": 346,
            "FTA": 423,
            "GP": 82
        },
        "1980-81": {
            "PPG": 17.5,
            "APG": 8.8,
            "RBG": 1.9,
            "SPG": 1.5,
            "BPG": 0.1,
            "TPG": 3.7,
            "PM": NaN,
            "MPG": 34.7,
            "FG_PCT": 0.478,
            "FG3_PCT": 0.306,
            "FT_PCT": 0.831,
            "FGM": 424,
            "FGA": 887,
            "FG3M": 11.0,
            "FG3A": 36.0,
            "FTM": 294,
            "FTA": 354,
            "GP": 66
        },
        "1981-82": {
            "PPG": 9.9,
            "APG": 6.3,
            "RBG": 1.5,
            "SPG": 0.9,
            "BPG": 0.0,
            "TPG": 2.7,
            "PM": NaN,
            "MPG": 27.1,
            "FG_PCT": 0.439,
            "FG3_PCT": 0.219,
            "FT_PCT": 0.819,
            "FGM": 285,
            "FGA": 649,
            "FG3M": 7.0,
            "FG3A": 32.0,
            "FTM": 136,
            "FTA": 166,
            "GP": 72
        },
        "1982-83": {
            "PPG": 6.8,
            "APG": 3.8,
            "RBG": 1.3,
            "SPG": 0.7,
            "BPG": 0.0,
            "TPG": 1.7,
            "PM": NaN,
            "MPG": 20.9,
            "FG_PCT": 0.479,
            "FG3_PCT": 0.111,
            "FT_PCT": 0.789,
            "FGM": 213,
            "FGA": 445,
            "FG3M": 1.0,
            "FG3A": 9.0,
            "FTM": 97,
            "FTA": 123,
            "GP": 77
        },
        "1983-84": {
            "PPG": 7.1,
            "APG": 5.1,
            "RBG": 1.7,
            "SPG": 0.7,
            "BPG": 0.1,
            "TPG": 1.7,
            "PM": NaN,
            "MPG": 24.9,
            "FG_PCT": 0.502,
            "FG3_PCT": 0.133,
            "FT_PCT": 0.838,
            "FGM": 236,
            "FGA": 470,
            "FG3M": 2.0,
            "FG3A": 15.0,
            "FTM": 98,
            "FTA": 117,
            "GP": 81
        },
        "1984-85": {
            "PPG": 1.8,
            "APG": 2.4,
            "RBG": 1.1,
            "SPG": 0.2,
            "BPG": 0.0,
            "TPG": 0.7,
            "PM": NaN,
            "MPG": 11.6,
            "FG_PCT": 0.298,
            "FG3_PCT": 0,
            "FT_PCT": 0.889,
            "FGM": 14,
            "FGA": 47,
            "FG3M": 0.0,
            "FG3A": 4.0,
            "FTM": 16,
            "FTA": 18,
            "GP": 25
        }
    },
    "playoff_stats": {
        "1978-79": {
            "PPG": 7.8,
            "APG": 5.8,
            "RBG": 2.4,
            "SPG": 2.4,
            "BPG": 0.0,
            "TPG": 3.0,
            "PM": NaN,
            "MPG": 28.6,
            "FG_PCT": 0.263,
            "FG3_PCT": NaN,
            "FT_PCT": 0.563,
            "FGM": 15,
            "FGA": 57,
            "FG3M": NaN,
            "FG3A": NaN,
            "FTM": 9,
            "FTA": 16,
            "GP": 5
        },
        "1979-80": {
            "PPG": 17.3,
            "APG": 8.7,
            "RBG": 2.0,
            "SPG": 1.7,
            "BPG": 0.0,
            "TPG": 4.0,
            "PM": NaN,
            "MPG": 36.7,
            "FG_PCT": 0.465,
            "FG3_PCT": 0.75,
            "FT_PCT": 0.818,
            "FGM": 20,
            "FGA": 43,
            "FG3M": 3.0,
            "FG3A": 4.0,
            "FTM": 9,
            "FTA": 11,
            "GP": 3
        },
        "1980-81": {
            "PPG": 7.8,
            "APG": 5.8,
            "RBG": 1.6,
            "SPG": 1.0,
            "BPG": 0.0,
            "TPG": 3.4,
            "PM": NaN,
            "MPG": 31.6,
            "FG_PCT": 0.429,
            "FG3_PCT": 0,
            "FT_PCT": 0.692,
            "FGM": 15,
            "FGA": 35,
            "FG3M": 0.0,
            "FG3A": 1.0,
            "FTM": 9,
            "FTA": 13,
            "GP": 5
        },
        "1982-83": {
            "PPG": 3.0,
            "APG": 0.5,
            "RBG": 0.0,
            "SPG": 0.0,
            "BPG": 0.0,
            "TPG": 0.0,
            "PM": NaN,
            "MPG": 2.5,
            "FG_PCT": 0,
            "FG3_PCT": NaN,
            "FT_PCT": 1.0,
            "FGM": 0,
            "FGA": 2,
            "FG3M": 0.0,
            "FG3A": 0.0,
            "FTM": 6,
            "FTA": 6,
            "GP": 2
        }
    },
    "specs": {
        "Height": 74,
        "Weight": "175",
        "Position": "Guard",
        "Teams": [
            "KCK",
            "NJN",
            "MIL",
            "TOT",
            "HOU"
        ],
        "DraftRound": "1",
        "DraftNumber": "2",
        "Active": false
    }
}