{
    "player_id": 78128,
    "full_name": "Ron Shavlik",
    "awards": {
        "NBA All-Star": [],
        "NBA All-Star Game MVP": [],
        "MVP": [],
        "All-NBA-First": [],
        "All-NBA-Second": [],
        "All-NBA-Third": [],
        "DPOY": [],
        "All-Defensive-First": [],
        "All-Defensive-Second": [],
        "ROY": [],
        "All-Rookie-First": [],
        "All-Rookie-Second": [],
        "Championships": [],
        "FMVP": [],
        "Olympic Gold": [],
        "Olympic Silver": [],
        "Olympic Bronze": []
    },
    "season_stats": {
        "1956-57": {
            "PPG": 1.4,
            "APG": 0.0,
            "RBG": 3.1,
            "SPG": 0.0,
            "BPG": 0.0,
            "TPG": 0.0,
            "PM": NaN,
            "MPG": 10.3,
            "FG_PCT": 0.182,
            "FG3_PCT": 0,
            "FT_PCT": 0.4,
            "FGM": 4,
            "FGA": 22,
            "FG3M": null,
            "FG3A": null,
            "FTM": 2,
            "FTA": 5,
            "GP": 7
        },
        "1957-58": {
            "PPG": 0.0,
            "APG": 0.0,
            "RBG": 1.0,
            "SPG": 0.0,
            "BPG": 0.0,
            "TPG": 0.0,
            "PM": NaN,
            "MPG": 2.0,
            "FG_PCT": 0,
            "FG3_PCT": 0,
            "FT_PCT": NaN,
            "FGM": 0,
            "FGA": 1,
            "FG3M": null,
            "FG3A": null,
            "FTM": 0,
            "FTA": 0,
            "GP": 1
        }
    },
    "playoff_stats": {},
    "specs": {
        "Height": 80,
        "Weight": "200",
        "Position": "Forward",
        "Teams": [
            "NYK"
        ],
        "DraftRound": "1",
        "DraftNumber": "4",
        "Active": false
    }
}