{
    "player_id": 101211,
    "full_name": "Stephen Graham",
    "awards": {
        "NBA All-Star": [],
        "NBA All-Star Game MVP": [],
        "MVP": [],
        "All-NBA-First": [],
        "All-NBA-Second": [],
        "All-NBA-Third": [],
        "DPOY": [],
        "All-Defensive-First": [],
        "All-Defensive-Second": [],
        "ROY": [],
        "All-Rookie-First": [],
        "All-Rookie-Second": [],
        "Championships": [],
        "FMVP": [],
        "Olympic Gold": [],
        "Olympic Silver": [],
        "Olympic Bronze": []
    },
    "season_stats": {
        "2005-06": {
            "PPG": 2.6,
            "APG": 0.3,
            "RBG": 1.2,
            "SPG": 0.2,
            "BPG": 0.1,
            "TPG": 0.6,
            "PM": 0.5,
            "MPG": 8.0,
            "FG_PCT": 0.389,
            "FG3_PCT": 0.2,
            "FT_PCT": 0.933,
            "FGM": 21,
            "FGA": 54,
            "FG3M": 2,
            "FG3A": 10,
            "FTM": 14,
            "FTA": 15,
            "GP": 22
        },
        "2006-07": {
            "PPG": 3.2,
            "APG": 0.4,
            "RBG": 1.5,
            "SPG": 0.3,
            "BPG": 0.1,
            "TPG": 0.9,
            "PM": -4.0,
            "MPG": 11.8,
            "FG_PCT": 0.425,
            "FG3_PCT": 0.273,
            "FT_PCT": 0.889,
            "FGM": 17,
            "FGA": 40,
            "FG3M": 3,
            "FG3A": 11,
            "FTM": 8,
            "FTA": 9,
            "GP": 14
        },
        "2007-08": {
            "PPG": 4.0,
            "APG": 0.4,
            "RBG": 1.0,
            "SPG": 0.2,
            "BPG": 0.0,
            "TPG": 0.5,
            "PM": 0.5,
            "MPG": 5.8,
            "FG_PCT": 0.586,
            "FG3_PCT": 0.5,
            "FT_PCT": 0.75,
            "FGM": 34,
            "FGA": 58,
            "FG3M": 7,
            "FG3A": 14,
            "FTM": 12,
            "FTA": 16,
            "GP": 22
        },
        "2008-09": {
            "PPG": 5.4,
            "APG": 0.6,
            "RBG": 1.8,
            "SPG": 0.2,
            "BPG": 0.1,
            "TPG": 0.9,
            "PM": -0.1,
            "MPG": 13.2,
            "FG_PCT": 0.414,
            "FG3_PCT": 0.303,
            "FT_PCT": 0.806,
            "FGM": 106,
            "FGA": 256,
            "FG3M": 20,
            "FG3A": 66,
            "FTM": 50,
            "FTA": 62,
            "GP": 52
        },
        "2009-10": {
            "PPG": 4.2,
            "APG": 0.3,
            "RBG": 1.9,
            "SPG": 0.3,
            "BPG": 0.1,
            "TPG": 0.5,
            "PM": -0.2,
            "MPG": 11.5,
            "FG_PCT": 0.496,
            "FG3_PCT": 0.32,
            "FT_PCT": 0.646,
            "FGM": 119,
            "FGA": 240,
            "FG3M": 16,
            "FG3A": 50,
            "FTM": 42,
            "FTA": 65,
            "GP": 70
        },
        "2010-11": {
            "PPG": 3.4,
            "APG": 0.7,
            "RBG": 2.1,
            "SPG": 0.2,
            "BPG": 0.0,
            "TPG": 0.6,
            "PM": -5.0,
            "MPG": 16.3,
            "FG_PCT": 0.405,
            "FG3_PCT": 0.238,
            "FT_PCT": 0.816,
            "FGM": 81,
            "FGA": 200,
            "FG3M": 5,
            "FG3A": 21,
            "FTM": 31,
            "FTA": 38,
            "GP": 59
        }
    },
    "playoff_stats": {
        "2009-10": {
            "PPG": 0.0,
            "APG": 0.5,
            "RBG": 0.0,
            "SPG": 0.5,
            "BPG": 0.0,
            "TPG": 0.5,
            "PM": -0.5,
            "MPG": 2.5,
            "FG_PCT": 0,
            "FG3_PCT": 0,
            "FT_PCT": 0,
            "FGM": 0,
            "FGA": 4,
            "FG3M": 0,
            "FG3A": 1,
            "FTM": 0,
            "FTA": 0,
            "GP": 2
        }
    },
    "specs": {
        "Height": 78,
        "Weight": "215",
        "Position": "Guard-Forward",
        "Teams": [
            "HOU",
            "CHI",
            "CLE",
            "TOT",
            "POR",
            "IND",
            "CHA",
            "NJN"
        ],
        "DraftRound": "Undrafted",
        "DraftNumber": "Undrafted",
        "Active": false
    }
}