{
    "player_id": 2216,
    "full_name": "Zach Randolph",
    "awards": {
        "NBA All-Star": [
            "2009-10",
            "2012-13"
        ],
        "NBA All-Star Game MVP": [],
        "MVP": [],
        "All-NBA-First": [],
        "All-NBA-Second": [],
        "All-NBA-Third": [
            "2010-11"
        ],
        "DPOY": [],
        "All-Defensive-First": [],
        "All-Defensive-Second": [],
        "ROY": [],
        "All-Rookie-First": [],
        "All-Rookie-Second": [],
        "Championships": [],
        "FMVP": [],
        "Olympic Gold": [],
        "Olympic Silver": [],
        "Olympic Bronze": []
    },
    "season_stats": {
        "2001-02": {
            "PPG": 2.8,
            "APG": 0.3,
            "RBG": 1.7,
            "SPG": 0.2,
            "BPG": 0.1,
            "TPG": 0.4,
            "PM": -0.5,
            "MPG": 5.8,
            "FG_PCT": 0.449,
            "FG3_PCT": 0,
            "FT_PCT": 0.667,
            "FGM": 48,
            "FGA": 107,
            "FG3M": 0,
            "FG3A": 0,
            "FTM": 18,
            "FTA": 27,
            "GP": 41
        },
        "2002-03": {
            "PPG": 8.4,
            "APG": 0.5,
            "RBG": 4.5,
            "SPG": 0.5,
            "BPG": 0.2,
            "TPG": 0.8,
            "PM": -1.2,
            "MPG": 16.9,
            "FG_PCT": 0.513,
            "FG3_PCT": 0,
            "FT_PCT": 0.758,
            "FGM": 264,
            "FGA": 515,
            "FG3M": 0,
            "FG3A": 5,
            "FTM": 122,
            "FTA": 161,
            "GP": 77
        },
        "2003-04": {
            "PPG": 20.1,
            "APG": 2.0,
            "RBG": 10.5,
            "SPG": 0.8,
            "BPG": 0.5,
            "TPG": 3.0,
            "PM": -0.7,
            "MPG": 37.9,
            "FG_PCT": 0.485,
            "FG3_PCT": 0.2,
            "FT_PCT": 0.761,
            "FGM": 663,
            "FGA": 1368,
            "FG3M": 1,
            "FG3A": 5,
            "FTM": 299,
            "FTA": 393,
            "GP": 81
        },
        "2004-05": {
            "PPG": 18.9,
            "APG": 1.9,
            "RBG": 9.6,
            "SPG": 0.7,
            "BPG": 0.4,
            "TPG": 2.4,
            "PM": -2.1,
            "MPG": 34.9,
            "FG_PCT": 0.448,
            "FG3_PCT": 0,
            "FT_PCT": 0.815,
            "FGM": 332,
            "FGA": 741,
            "FG3M": 0,
            "FG3A": 6,
            "FTM": 207,
            "FTA": 254,
            "GP": 46
        },
        "2005-06": {
            "PPG": 18.0,
            "APG": 1.9,
            "RBG": 8.0,
            "SPG": 0.8,
            "BPG": 0.2,
            "TPG": 2.2,
            "PM": -5.9,
            "MPG": 34.4,
            "FG_PCT": 0.436,
            "FG3_PCT": 0.291,
            "FT_PCT": 0.714,
            "FGM": 536,
            "FGA": 1229,
            "FG3M": 16,
            "FG3A": 55,
            "FTM": 245,
            "FTA": 343,
            "GP": 74
        },
        "2006-07": {
            "PPG": 23.6,
            "APG": 2.2,
            "RBG": 10.1,
            "SPG": 0.8,
            "BPG": 0.2,
            "TPG": 3.2,
            "PM": -1.9,
            "MPG": 35.7,
            "FG_PCT": 0.467,
            "FG3_PCT": 0.292,
            "FT_PCT": 0.819,
            "FGM": 600,
            "FGA": 1286,
            "FG3M": 14,
            "FG3A": 48,
            "FTM": 394,
            "FTA": 481,
            "GP": 68
        },
        "2007-08": {
            "PPG": 17.6,
            "APG": 2.0,
            "RBG": 10.3,
            "SPG": 0.9,
            "BPG": 0.2,
            "TPG": 2.7,
            "PM": -4.0,
            "MPG": 32.5,
            "FG_PCT": 0.459,
            "FG3_PCT": 0.275,
            "FT_PCT": 0.772,
            "FGM": 486,
            "FGA": 1058,
            "FG3M": 22,
            "FG3A": 80,
            "FTM": 223,
            "FTA": 289,
            "GP": 69
        },
        "2008-09": {
            "PPG": 20.8,
            "APG": 2.1,
            "RBG": 10.1,
            "SPG": 0.9,
            "BPG": 0.3,
            "TPG": 2.3,
            "PM": -2.9,
            "MPG": 35.1,
            "FG_PCT": 0.475,
            "FG3_PCT": 0.33,
            "FT_PCT": 0.734,
            "FGM": 415,
            "FGA": 873,
            "FG3M": 32,
            "FG3A": 97,
            "FTM": 179,
            "FTA": 244,
            "GP": 50
        },
        "2009-10": {
            "PPG": 20.8,
            "APG": 1.8,
            "RBG": 11.7,
            "SPG": 1.0,
            "BPG": 0.4,
            "TPG": 2.1,
            "PM": 0.2,
            "MPG": 37.7,
            "FG_PCT": 0.488,
            "FG3_PCT": 0.288,
            "FT_PCT": 0.778,
            "FGM": 652,
            "FGA": 1336,
            "FG3M": 15,
            "FG3A": 52,
            "FTM": 362,
            "FTA": 465,
            "GP": 81
        },
        "2010-11": {
            "PPG": 20.1,
            "APG": 2.2,
            "RBG": 12.2,
            "SPG": 0.8,
            "BPG": 0.3,
            "TPG": 2.0,
            "PM": 3.5,
            "MPG": 36.3,
            "FG_PCT": 0.503,
            "FG3_PCT": 0.186,
            "FT_PCT": 0.758,
            "FGM": 598,
            "FGA": 1188,
            "FG3M": 8,
            "FG3A": 43,
            "FTM": 300,
            "FTA": 396,
            "GP": 75
        },
        "2011-12": {
            "PPG": 11.6,
            "APG": 1.7,
            "RBG": 8.0,
            "SPG": 0.8,
            "BPG": 0.1,
            "TPG": 1.4,
            "PM": 4.1,
            "MPG": 26.2,
            "FG_PCT": 0.463,
            "FG3_PCT": 0.25,
            "FT_PCT": 0.659,
            "FGM": 132,
            "FGA": 285,
            "FG3M": 2,
            "FG3A": 8,
            "FTM": 58,
            "FTA": 88,
            "GP": 28
        },
        "2012-13": {
            "PPG": 15.4,
            "APG": 1.4,
            "RBG": 11.2,
            "SPG": 0.8,
            "BPG": 0.4,
            "TPG": 2.0,
            "PM": 3.9,
            "MPG": 34.3,
            "FG_PCT": 0.46,
            "FG3_PCT": 0.087,
            "FT_PCT": 0.75,
            "FGM": 471,
            "FGA": 1024,
            "FG3M": 2,
            "FG3A": 23,
            "FTM": 225,
            "FTA": 300,
            "GP": 76
        },
        "2013-14": {
            "PPG": 17.4,
            "APG": 2.5,
            "RBG": 10.1,
            "SPG": 0.7,
            "BPG": 0.3,
            "TPG": 2.3,
            "PM": 2.1,
            "MPG": 34.2,
            "FG_PCT": 0.467,
            "FG3_PCT": 0.1,
            "FT_PCT": 0.742,
            "FGM": 560,
            "FGA": 1198,
            "FG3M": 2,
            "FG3A": 20,
            "FTM": 250,
            "FTA": 337,
            "GP": 79
        },
        "2014-15": {
            "PPG": 16.1,
            "APG": 2.2,
            "RBG": 10.5,
            "SPG": 1.0,
            "BPG": 0.2,
            "TPG": 2.2,
            "PM": 4.9,
            "MPG": 32.5,
            "FG_PCT": 0.487,
            "FG3_PCT": 0.35,
            "FT_PCT": 0.765,
            "FGM": 454,
            "FGA": 932,
            "FG3M": 7,
            "FG3A": 20,
            "FTM": 228,
            "FTA": 298,
            "GP": 71
        },
        "2015-16": {
            "PPG": 15.3,
            "APG": 2.1,
            "RBG": 7.8,
            "SPG": 0.6,
            "BPG": 0.2,
            "TPG": 1.5,
            "PM": -0.2,
            "MPG": 29.6,
            "FG_PCT": 0.475,
            "FG3_PCT": 0.231,
            "FT_PCT": 0.796,
            "FGM": 431,
            "FGA": 907,
            "FG3M": 6,
            "FG3A": 26,
            "FTM": 172,
            "FTA": 216,
            "GP": 68
        },
        "2016-17": {
            "PPG": 14.1,
            "APG": 1.7,
            "RBG": 8.2,
            "SPG": 0.5,
            "BPG": 0.1,
            "TPG": 1.4,
            "PM": 1.0,
            "MPG": 24.5,
            "FG_PCT": 0.449,
            "FG3_PCT": 0.223,
            "FT_PCT": 0.731,
            "FGM": 433,
            "FGA": 964,
            "FG3M": 21,
            "FG3A": 94,
            "FTM": 141,
            "FTA": 193,
            "GP": 73
        },
        "2017-18": {
            "PPG": 14.5,
            "APG": 2.2,
            "RBG": 6.7,
            "SPG": 0.7,
            "BPG": 0.2,
            "TPG": 2.0,
            "PM": -6.0,
            "MPG": 25.6,
            "FG_PCT": 0.473,
            "FG3_PCT": 0.347,
            "FT_PCT": 0.785,
            "FGM": 361,
            "FGA": 763,
            "FG3M": 51,
            "FG3A": 147,
            "FTM": 84,
            "FTA": 107,
            "GP": 59
        }
    },
    "playoff_stats": {
        "2001-02": {
            "PPG": 0.0,
            "APG": 0.0,
            "RBG": 0.0,
            "SPG": 0.0,
            "BPG": 0.0,
            "TPG": 0.0,
            "PM": 0.0,
            "MPG": 1.0,
            "FG_PCT": 0,
            "FG3_PCT": 0,
            "FT_PCT": 0,
            "FGM": 0,
            "FGA": 0,
            "FG3M": 0,
            "FG3A": 0,
            "FTM": 0,
            "FTA": 0,
            "GP": 1
        },
        "2002-03": {
            "PPG": 13.9,
            "APG": 1.6,
            "RBG": 8.7,
            "SPG": 0.4,
            "BPG": 0.3,
            "TPG": 1.9,
            "PM": 4.0,
            "MPG": 29.3,
            "FG_PCT": 0.525,
            "FG3_PCT": 0,
            "FT_PCT": 0.892,
            "FGM": 32,
            "FGA": 61,
            "FG3M": 0,
            "FG3A": 0,
            "FTM": 33,
            "FTA": 37,
            "GP": 7
        },
        "2010-11": {
            "PPG": 22.2,
            "APG": 2.4,
            "RBG": 10.8,
            "SPG": 1.1,
            "BPG": 0.8,
            "TPG": 2.1,
            "PM": 0.6,
            "MPG": 39.6,
            "FG_PCT": 0.446,
            "FG3_PCT": 0.25,
            "FT_PCT": 0.821,
            "FGM": 100,
            "FGA": 224,
            "FG3M": 2,
            "FG3A": 8,
            "FTM": 87,
            "FTA": 106,
            "GP": 13
        },
        "2011-12": {
            "PPG": 13.7,
            "APG": 0.9,
            "RBG": 9.9,
            "SPG": 1.0,
            "BPG": 0.6,
            "TPG": 1.6,
            "PM": 4.3,
            "MPG": 35.4,
            "FG_PCT": 0.42,
            "FG3_PCT": 0,
            "FT_PCT": 0.629,
            "FGM": 37,
            "FGA": 88,
            "FG3M": 0,
            "FG3A": 4,
            "FTM": 22,
            "FTA": 35,
            "GP": 7
        },
        "2012-13": {
            "PPG": 17.4,
            "APG": 1.6,
            "RBG": 10.0,
            "SPG": 0.7,
            "BPG": 0.5,
            "TPG": 2.1,
            "PM": 2.7,
            "MPG": 36.9,
            "FG_PCT": 0.46,
            "FG3_PCT": 0,
            "FT_PCT": 0.67,
            "FGM": 99,
            "FGA": 215,
            "FG3M": 0,
            "FG3A": 1,
            "FTM": 63,
            "FTA": 94,
            "GP": 15
        },
        "2013-14": {
            "PPG": 18.2,
            "APG": 2.3,
            "RBG": 8.7,
            "SPG": 0.8,
            "BPG": 0.2,
            "TPG": 1.7,
            "PM": -5.3,
            "MPG": 39.0,
            "FG_PCT": 0.404,
            "FG3_PCT": 0,
            "FT_PCT": 0.61,
            "FGM": 42,
            "FGA": 104,
            "FG3M": 0,
            "FG3A": 1,
            "FTM": 25,
            "FTA": 41,
            "GP": 6
        },
        "2014-15": {
            "PPG": 15.6,
            "APG": 2.1,
            "RBG": 8.5,
            "SPG": 0.5,
            "BPG": 0.0,
            "TPG": 2.1,
            "PM": -0.6,
            "MPG": 34.7,
            "FG_PCT": 0.423,
            "FG3_PCT": 0.2,
            "FT_PCT": 0.879,
            "FGM": 71,
            "FGA": 168,
            "FG3M": 1,
            "FG3A": 5,
            "FTM": 29,
            "FTA": 33,
            "GP": 11
        },
        "2015-16": {
            "PPG": 13.0,
            "APG": 1.8,
            "RBG": 8.8,
            "SPG": 0.2,
            "BPG": 0.0,
            "TPG": 1.8,
            "PM": -14.2,
            "MPG": 30.0,
            "FG_PCT": 0.371,
            "FG3_PCT": 0,
            "FT_PCT": 0.857,
            "FGM": 23,
            "FGA": 62,
            "FG3M": 0,
            "FG3A": 0,
            "FTM": 6,
            "FTA": 7,
            "GP": 4
        },
        "2016-17": {
            "PPG": 13.2,
            "APG": 0.7,
            "RBG": 8.2,
            "SPG": 0.8,
            "BPG": 0.3,
            "TPG": 1.2,
            "PM": -6.0,
            "MPG": 31.8,
            "FG_PCT": 0.422,
            "FG3_PCT": 0.143,
            "FT_PCT": 0.727,
            "FGM": 35,
            "FGA": 83,
            "FG3M": 1,
            "FG3A": 7,
            "FTM": 8,
            "FTA": 11,
            "GP": 6
        }
    },
    "specs": {
        "Height": 81,
        "Weight": "250",
        "Position": "Forward",
        "Teams": [
            "POR",
            "NYK",
            "LAC",
            "TOT",
            "MEM",
            "SAC"
        ],
        "DraftRound": "1",
        "DraftNumber": "19",
        "Active": false
    }
}